django_mongo_coupons-0.0.1.dev2.dist-info/DESCRIPTION.rst
django_mongo_coupons-0.0.1.dev2.dist-info/METADATA
django_mongo_coupons-0.0.1.dev2.dist-info/RECORD
django_mongo_coupons-0.0.1.dev2.dist-info/WHEEL
django_mongo_coupons-0.0.1.dev2.dist-info/metadata.json
django_mongo_coupons-0.0.1.dev2.dist-info/top_level.txt
mongo_coupons/__init__.py
mongo_coupons/coupon_settings.py
mongo_coupons/couponserializer.py
mongo_coupons/models.py
mongo_coupons/serializer.py
mongo_coupons/urls.py
mongo_coupons/views.py
tests/__init__.py
tests/settings.py
tests/test_models.py
tests/test_use_cases.py
